modelcdb/cmdb.py
modelcdb-0.1.dist-info/METADATA
modelcdb-0.1.dist-info/WHEEL
modelcdb-0.1.dist-info/top_level.txt
modelcdb-0.1.dist-info/RECORD
